metasys/__init__.py
metasys/base.py
metasys/exceptions.py
metasys-0.0.1.dist-info/METADATA
metasys-0.0.1.dist-info/WHEEL
metasys-0.0.1.dist-info/RECORD
