Metadata-Version: 2.1
Name: metasys
Version: 0.0.1
Summary: metasys module
Author-email: Felix <tinylambda@gmail.com>
License: MIT License
Classifier: Operating System :: OS Independent
Classifier: Programming Language :: Python
Classifier: Programming Language :: Python :: 3
Classifier: Programming Language :: Python :: 3 :: Only
Requires-Python: >=3.11
Provides-Extra: dev
Requires-Dist: black==23.3.0; extra == 'dev'
Requires-Dist: pre-commit<3.0.0,>=2.17.0; extra == 'dev'
Provides-Extra: test
Requires-Dist: pytest<8.0.0,>=7.1.3; extra == 'test'
